odb2psql/__init__.py
odb2psql/__main__.py
odb2psql/to_psql.py
tests/__init__.py
tests/test_odb2psql.py
odb2psql-0.0.2.dist-info/LICENSE
odb2psql-0.0.2.dist-info/METADATA
odb2psql-0.0.2.dist-info/WHEEL
odb2psql-0.0.2.dist-info/top_level.txt
odb2psql-0.0.2.dist-info/RECORD
