Metadata-Version: 2.1
Name: odb2psql
Version: 0.0.2
Summary: Converter from OpenOffice *.odb to PostgreSQL *.sql
Home-page: https://github.com/remoteworkerid/odb2psql
Author: Eko S. Wibowo
Author-email: swdev.bali@gmail.com
License: UNKNOWN
Platform: UNKNOWN
Classifier: Programming Language :: Python :: 3
Classifier: License :: OSI Approved :: GNU General Public License v3 (GPLv3)
Classifier: Operating System :: OS Independent
Classifier: Development Status :: 4 - Beta
Requires-Python: >=3.6
Requires-Dist: click
